helloworld_demo_colewilson/__init__.py
helloworld_demo_colewilson/__main__.py
helloworld_demo_colewilson-0.0.1.data/scripts/hello
helloworld_demo_colewilson-0.0.1.dist-info/METADATA
helloworld_demo_colewilson-0.0.1.dist-info/WHEEL
helloworld_demo_colewilson-0.0.1.dist-info/entry_points.txt
helloworld_demo_colewilson-0.0.1.dist-info/top_level.txt
helloworld_demo_colewilson-0.0.1.dist-info/RECORD
